onvif_parsers/__init__.py
onvif_parsers/model.py
onvif_parsers/py.typed
onvif_parsers/registry.py
onvif_parsers-1.0.0.dist-info/licenses/LICENSE
onvif_parsers-1.0.0.dist-info/METADATA
onvif_parsers-1.0.0.dist-info/WHEEL
onvif_parsers-1.0.0.dist-info/top_level.txt
onvif_parsers-1.0.0.dist-info/RECORD
