Metadata-Version: 2.4
Name: onvif-parsers
Version: 1.0.0
Summary: Parsers for ONVIF events
Author-email: Open Video Libs <openvideolibs@koston.org>
License: Apache Software License 2.0
Project-URL: Bug Tracker, https://github.com/openvideolibs/onvif-parsers/issues
Project-URL: Changelog, https://github.com/openvideolibs/onvif-parsers/blob/main/CHANGELOG.md
Project-URL: documentation, https://onvif-parsers.readthedocs.io
Project-URL: repository, https://github.com/openvideolibs/onvif-parsers
Classifier: Development Status :: 2 - Pre-Alpha
Classifier: Intended Audience :: Developers
Classifier: Natural Language :: English
Classifier: Operating System :: OS Independent
Classifier: Programming Language :: Python :: 3.10
Classifier: Programming Language :: Python :: 3.11
Classifier: Programming Language :: Python :: 3.12
Classifier: Programming Language :: Python :: 3.13
Classifier: Programming Language :: Python :: 3.14
Classifier: Topic :: Software Development :: Libraries
Requires-Python: >=3.10
License-File: LICENSE
Dynamic: license-file
